anylog/__init__.py
tests/__init__.py
anylog-0.0.1.dist-info/METADATA
anylog-0.0.1.dist-info/WHEEL
anylog-0.0.1.dist-info/top_level.txt
anylog-0.0.1.dist-info/RECORD
