Metadata-Version: 2.1
Name: anylog
Version: 0.0.1
Summary: Faster, small and easy logging framework
Home-page: UNKNOWN
Author: Oleksandr Popov
Author-email: oleksandr.popov@outlook.com
License: UNKNOWN
Platform: UNKNOWN
Classifier: Programming Language :: Python :: 3
Classifier: License :: OSI Approved :: MIT License
Classifier: Operating System :: OS Independent
